MANIFEST.in
README.txt
setup.cfg
setup.py
Products/__init__.py
Products.CSSManager.egg-info/PKG-INFO
Products.CSSManager.egg-info/SOURCES.txt
Products.CSSManager.egg-info/dependency_links.txt
Products.CSSManager.egg-info/entry_points.txt
Products.CSSManager.egg-info/namespace_packages.txt
Products.CSSManager.egg-info/not-zip-safe
Products.CSSManager.egg-info/requires.txt
Products.CSSManager.egg-info/top_level.txt
Products/CSSManager/CREDITS.txt
Products/CSSManager/LICENSE.GPL
Products/CSSManager/README.txt
Products/CSSManager/VERSION.txt
Products/CSSManager/__init__.py
Products/CSSManager/config.py
Products/CSSManager/css_manager_logo.gif
Products/CSSManager/css_tool.py
Products/CSSManager/skins.py
Products/CSSManager/tool.gif
Products/CSSManager/Extensions/Install.py
Products/CSSManager/Extensions/__init__.py
Products/CSSManager/skins/CSSManager_Images/crosshairs.png
Products/CSSManager/skins/CSSManager_Images/css_manager_logo.gif
Products/CSSManager/skins/CSSManager_Images/h.png
Products/CSSManager/skins/CSSManager_Images/position.png
Products/CSSManager/skins/CSSManager_Images/sv.png
Products/CSSManager/skins/CSSManager_Scripts/pickers.js
Products/CSSManager/skins/CSSManager_Scripts/scriptz.js
Products/CSSManager/skins/CSSManager_Templates/base_properties_help.pt
Products/CSSManager/skins/CSSManager_Templates/cssmanager_widget_borderStyle.pt
Products/CSSManager/skins/CSSManager_Templates/cssmanager_widget_color.pt
Products/CSSManager/skins/CSSManager_Templates/cssmanager_widget_fileUploadRename.pt
Products/CSSManager/skins/CSSManager_Templates/cssmanager_widget_fontFamily.pt
Products/CSSManager/skins/CSSManager_Templates/cssmanager_widget_text.pt
Products/CSSManager/skins/CSSManager_Templates/cssmanager_widget_textTransform.pt
Products/CSSManager/skins/CSSManager_Templates/pick_color.dtml
Products/CSSManager/skins/CSSManager_Templates/pick_color2.dtml
Products/CSSManager/skins/CSSManager_Templates/pick_font.dtml
Products/CSSManager/skins/CSSManager_Templates/popup.js.dtml
Products/CSSManager/skins/CSSManager_Templates/prefs_cssmanager_form.cpt
Products/CSSManager/skins/CSSManager_Templates/prefs_cssmanager_form.cpt.metadata
Products/CSSManager/www/cssconfig.zpt
dist/Products.CSSManager-0.93dev-py2.4.egg
docs/HISTORY.txt
docs/INSTALL.txt
docs/LICENSE.GPL
docs/LICENSE.txt