Metadata-Version: 1.0
Name: Products.CSSManager
Version: 0.93a1
Summary: CSSManager is a simple add-on for managing CSS properties exposed by Plone 3 and 2
Home-page: https://weblion.psu.edu/svn/weblion/weblion/Products.CSSManager
Author: WebLion group at Penn State University
Author-email: webmaster@weblion.psu.edu
License: GPL
Keywords: web zope plone theme
Platform: UNKNOWN
Classifier: Framework :: Plone
Classifier: Programming Language :: Python
Classifier: Topic :: Software Development :: Libraries :: Python Modules
